routerl/__init__.py
routerl/keychain.py
routerl/environment/__init__.py
routerl/environment/agent.py
routerl/environment/agent_generation.py
routerl/environment/defaults.json
routerl/environment/environment.py
routerl/environment/observations.py
routerl/environment/simulator.py
routerl/human_learning/__init__.py
routerl/human_learning/learning_model.py
routerl/human_learning/registry.py
routerl/networks/default_ods.json
routerl/networks/arterial/arterial.con.xml
routerl/networks/arterial/arterial.edg.xml
routerl/networks/arterial/arterial.net.xml
routerl/networks/arterial/arterial.nod.xml
routerl/networks/arterial/arterial.rou.xml
routerl/networks/arterial/arterial.tll.xml
routerl/networks/arterial/arterial.typ.xml
routerl/networks/cologne/cologne.con.xml
routerl/networks/cologne/cologne.edg.xml
routerl/networks/cologne/cologne.net.xml
routerl/networks/cologne/cologne.nod.xml
routerl/networks/cologne/cologne.rou.xml
routerl/networks/cologne/cologne.tll.xml
routerl/networks/cologne/cologne.typ.xml
routerl/networks/csomor/csomor.con.xml
routerl/networks/csomor/csomor.edg.xml
routerl/networks/csomor/csomor.net.xml
routerl/networks/csomor/csomor.nod.xml
routerl/networks/csomor/csomor.rou.xml
routerl/networks/csomor/csomor.tll.xml
routerl/networks/csomor/csomor.typ.xml
routerl/networks/grid/grid.con.xml
routerl/networks/grid/grid.edg.xml
routerl/networks/grid/grid.net.xml
routerl/networks/grid/grid.nod.xml
routerl/networks/grid/grid.rou.xml
routerl/networks/grid/grid.tll.xml
routerl/networks/grid6/grid6.con.xml
routerl/networks/grid6/grid6.edg.xml
routerl/networks/grid6/grid6.net.xml
routerl/networks/grid6/grid6.nod.xml
routerl/networks/grid6/grid6.rou.xml
routerl/networks/grid6/grid6.tll.xml
routerl/networks/ingolstadt/ingolstadt.con.xml
routerl/networks/ingolstadt/ingolstadt.edg.xml
routerl/networks/ingolstadt/ingolstadt.net.xml
routerl/networks/ingolstadt/ingolstadt.nod.xml
routerl/networks/ingolstadt/ingolstadt.rou.xml
routerl/networks/ingolstadt/ingolstadt.tll.xml
routerlurb-1.0.0.dist-info/licenses/LICENSE.txt
routerlurb-1.0.0.dist-info/METADATA
routerlurb-1.0.0.dist-info/WHEEL
routerlurb-1.0.0.dist-info/top_level.txt
routerlurb-1.0.0.dist-info/RECORD
